gen_names_grizzy
