Metadata-Version: 1.0
Name: get-names-grizzy
Version: 0.1.1
Summary: My first library
Home-page: http://google.pl/
Author: Lukasz Nowak
Author-email: lukasz.nowak1@gmail.com
License: UNKNOWN
Keywords: names and len
Platform: UNKNOWN
